{
  "1310_0": {
    "titleCN": "名侦探柯南",
    "titleJP": "名探偵コナン",
    "officalSite": "http://www.ytv.co.jp/conan/",
    "weekDayJP": 6,
    "weekDayCN": 0,
    "timeJP": "1800",
    "timeCN": "",
    "onAirSite": [
      "http://www.acfun.tv/a/aa127",
      "http://www.iqiyi.com/dongman/mztkngyb.html"
    ],
    "newBgm": false,
    "bgmId": 899,
    "showDate": "1996-01-08"
  },
  "1310_1": {
    "titleCN": "海贼王",
    "titleJP": "ONE PIECE",
    "officalSite": "http://www.toei-anim.co.jp/tv/onep/",
    "weekDayJP": 0,
    "weekDayCN": 0,
    "timeJP": "0930",
    "timeCN": "",
    "onAirSite": [
      "http://www.bilibili.com/sp/海贼王",
      "http://www.acfun.tv/a/aa126",
      "http://tv.sohu.com/s2013/onepiece/"
    ],
    "newBgm": false,
    "bgmId": 975,
    "showDate": "1999-10-20"
  },
  "1310_2": {
    "titleCN": "火影忍者 疾风传",
    "titleJP": "NARUTO -ナルト- 疾風伝",
    "officalSite": "http://www.tv-tokyo.co.jp/anime/naruto/index2.html",
    "weekDayJP": 4,
    "weekDayCN": 4,
    "timeJP": "1830",
    "timeCN": "1900",
    "onAirSite": [
      "http://www.tudou.com/albumcover/Lqfme5hSolM.html",
      "http://www.bilibili.com/sp/火影忍者"
    ],
    "newBgm": false,
    "bgmId": 2782,
    "showDate": "2007-02-15"
  },
  "1310_3": {
    "titleCN": "偶像活动! 二期",
    "titleJP": "アイカツ!アイドルカツドウ!",
    "officalSite": "http://www.aikatsu.net",
    "weekDayJP": 4,
    "weekDayCN": 5,
    "timeJP": "1800",
    "timeCN": "",
    "onAirSite": [
      "http://www.bilibili.com/sp/偶像活动"
    ],
    "newBgm": true,
    "bgmId": 139317,
    "showDate": "2013-10-03"
  },
  "1310_4": {
    "titleCN": "王者天下2",
    "titleJP": "キングダム2",
    "officalSite": "http://www9.nhk.or.jp/anime/kingdom2/",
    "weekDayJP": 6,
    "weekDayCN": 0,
    "timeJP": "2300",
    "timeCN": "",
    "onAirSite": [
      "http://www.bilibili.com/sp/王者天下",
      "http://www.acfun.tv/a/aa112"
    ],
    "newBgm": false,
    "bgmId": 62281,
    "showDate": "2013-06-08"
  },
  "1310_5": {
    "titleCN": "BLAZBLUE Alter Memory",
    "titleJP": "BLAZBLUE Alter Memory",
    "officalSite": "http://blazblue-am.jp/",
    "weekDayJP": 3,
    "weekDayCN": 3,
    "timeJP": "0030",
    "timeCN": "0400",
    "onAirSite": [
      "http://tv.sohu.com/s2013/blazblue1/",
      "http://www.acfun.tv/a/aa67"
    ],
    "newBgm": true,
    "bgmId": 73825,
    "showDate": "2013-10-09"
  },
  "1310_6": {
    "titleCN": "苍蓝钢铁的琶音",
    "titleJP": "蒼き鋼のアルペジオ ‐アルス・ノヴァ‐",
    "officalSite": "http://www.aokihagane.com/",
    "weekDayJP": 2,
    "weekDayCN": 3,
    "timeJP": "0155",
    "timeCN": "",
    "onAirSite": [
      "http://www.bilibili.com/sp/苍蓝钢铁的琶音",
      "http://www.acfun.tv/a/aa75"
    ],
    "newBgm": true,
    "bgmId": 74663,
    "showDate": "2013-10-08"
  },
  "1310_7": {
    "titleCN": "革命机Valvrave 2期",
    "titleJP": "革命機ヴァルヴレイヴ 2ndシーズン",
    "officalSite": "http://www.valvrave.com/",
    "weekDayJP": 5,
    "weekDayCN": 5,
    "timeJP": "0035",
    "timeCN": "0435",
    "onAirSite": [
      "http://www.iqiyi.com/dongman/vvv.html",
      "http://www.bilibili.com/sp/VALVRAVE革命机",
      "http://www.acfun.tv/a/aa2453"
    ],
    "newBgm": true,
    "bgmId": 70131,
    "showDate": "2013-10-11"
  },
  "1310_8": {
    "titleCN": "萌萌侵略者",
    "titleJP": "アウトブレイク・カンパニー",
    "officalSite": "http://www.tbs.co.jp/anime/obc/",
    "weekDayJP": 5,
    "weekDayCN": 5,
    "timeJP": "0028",
    "timeCN": "0400",
    "onAirSite": [
      "http://tv.sohu.com/s2013/mmqlz/",
      "http://www.bilibili.com/sp/萌萌侵略者",
      "http://www.acfun.tv/a/aa81"
    ],
    "newBgm": true,
    "bgmId": 78406,
    "showDate": "2013-10-04"
  },
  "1310_9": {
    "titleCN": "Kill la Kill",
    "titleJP": "キルラキル",
    "officalSite": "http://www.kill-la-kill.jp/",
    "weekDayJP": 5,
    "weekDayCN": 5,
    "timeJP": "0105",
    "timeCN": "0110",
    "onAirSite": [
      "http://comic.letv.com/zt/KLK/index.shtml",
      "http://www.bilibili.com/sp/斩服少女",
      "http://www.acfun.tv/a/aa98"
    ],
    "newBgm": true,
    "bgmId": 72941,
    "showDate": "2013-10-04"
  },
  "1310_10": {
    "titleCN": "IS <Infinite Stratos> 2",
    "titleJP": "IS＜インフィニット・ストラトス＞2",
    "officalSite": "http://www.tbs.co.jp/anime/is2/",
    "weekDayJP": 5,
    "weekDayCN": 5,
    "timeJP": "0058",
    "timeCN": "0430",
    "onAirSite": [
      "http://tv.sohu.com/s2013/is2/",
      "http://www.bilibili.com/sp/INFINITE%20STRATOS",
      "http://www.acfun.tv/a/aa80"
    ],
    "newBgm": true,
    "bgmId": 68022,
    "showDate": "2013-10-04"
  },
  "1310_11": {
    "titleCN": "京骚戏画",
    "titleJP": "京騒戯画",
    "officalSite": "http://www.kyousougiga-tv.com/",
    "weekDayJP": 4,
    "weekDayCN": 5,
    "timeJP": "0030",
    "timeCN": "",
    "onAirSite": [
      "http://www.bilibili.com/sp/京骚戏画",
      "http://www.acfun.tv/a/aa79"
    ],
    "newBgm": true,
    "bgmId": 14749,
    "showDate": "2013-10-03"
  },
  "1310_12": {
    "titleCN": "卡片战斗先导者 LinkJoker篇",
    "titleJP": "カードファイト!! ヴァンガード　リンクジョーカー編",
    "officalSite": "http://www.tv-tokyo.co.jp/anime/cf-vanguard-lj/",
    "weekDayJP": 0,
    "weekDayCN": 1,
    "timeJP": "0900",
    "timeCN": "",
    "onAirSite": [
      "http://www.bilibili.com/sp/卡片战斗先导者"
    ],
    "newBgm": false,
    "bgmId": 55783,
    "showDate": "2013-01-13"
  },
  "1310_13": {
    "titleCN": "圣灵破碎者",
    "titleJP": "ガイストクラッシャー",
    "officalSite": "http://gaist-anime.com/",
    "weekDayJP": 3,
    "weekDayCN": 4,
    "timeJP": "1700",
    "timeCN": "",
    "onAirSite": [
      "http://www.bilibili.com/sp/圣灵破碎者"
    ],
    "newBgm": true,
    "bgmId": 79873,
    "showDate": "2013-10-02"
  },
  "1310_14": {
    "titleCN": "探险DRILAND 1000年的真宝",
    "titleJP": "探検ドリランド -1000年の真宝-",
    "officalSite": "http://www.tv-tokyo.co.jp/anime/driland2/",
    "weekDayJP": 6,
    "weekDayCN": 0,
    "timeJP": "0930",
    "timeCN": "",
    "onAirSite": [
      "http://www.bilibili.com/sp/探险DRILAND"
    ],
    "newBgm": false,
    "bgmId": 66409,
    "showDate": "2013-04-06"
  },
  "1310_15": {
    "titleCN": "美妙旋律 Rainbow Live",
    "titleJP": "プリティーリズム・レインボーライブ",
    "officalSite": "http://www.tv-tokyo.co.jp/anime/prettyrhythm/",
    "weekDayJP": 6,
    "weekDayCN": 0,
    "timeJP": "0900",
    "timeCN": "",
    "onAirSite": [
      "http://www.bilibili.com/sp/美妙旋律%20彩虹之梦#S-267"
    ],
    "newBgm": false,
    "bgmId": 62285,
    "showDate": "2013-04-06"
  },
  "1310_16": {
    "titleCN": "COPPELION 核爆默示录",
    "titleJP": "COPPELION(コッペリオン)",
    "officalSite": "http://www.starchild.co.jp/special/coppelion/top.html",
    "weekDayJP": 3,
    "weekDayCN": 3,
    "timeJP": "2000",
    "timeCN": "2100",
    "onAirSite": [
      "http://v.qq.com/cover/o/ox39rizb1w9cbv1.html",
      "http://www.bilibili.com/sp/核爆默示录",
      "http://www.acfun.tv/a/aa94"
    ],
    "newBgm": true,
    "bgmId": 10463,
    "showDate": "2013-10-02"
  },
  "1310_17": {
    "titleCN": "高达Build Fighters",
    "titleJP": "ガンダムビルドファイターズ",
    "officalSite": "http://gundam-bf.net/",
    "weekDayJP": 1,
    "weekDayCN": 1,
    "timeJP": "1700",
    "timeCN": "1900",
    "onAirSite": [
      "http://www.iqiyi.com/a_19rrgjaks5.html",
      "http://www.bilibili.com/sp/高达BUILD%20FIGHTERS",
      "http://www.acfun.tv/a/aa90"
    ],
    "newBgm": true,
    "bgmId": 77171,
    "showDate": "2013-10-07"
  },
  "1310_18": {
    "titleCN": "物语系列 第二季",
    "titleJP": "＜物語＞シリーズ セカンドシーズン",
    "officalSite": "http://www.monogatari-series.com/2ndseason/",
    "weekDayJP": 6,
    "weekDayCN": 0,
    "timeJP": "2300",
    "timeCN": "0000",
    "onAirSite": [
      "http://comic.letv.com/zt/wuyu/index.shtml",
      "http://www.bilibili.com/sp/物语系列",
      "http://www.acfun.tv/a/aa118"
    ],
    "newBgm": false,
    "bgmId": 68812,
    "showDate": "2013-07-06"
  },
  "1310_19": {
    "titleCN": "Golden Time 青春纪行",
    "titleJP": "ゴールデンタイム",
    "officalSite": "http://golden-time.jp/",
    "weekDayJP": 5,
    "weekDayCN": 5,
    "timeJP": "0135",
    "timeCN": "0230",
    "onAirSite": [
      "http://v.qq.com/detail/r/rur1k9y16jaqici.html",
      "http://www.bilibili.com/sp/金色时光",
      "http://www.acfun.tv/a/aa101"
    ],
    "newBgm": true,
    "bgmId": 68031,
    "showDate": "2013-10-04"
  },
  "1310_20": {
    "titleCN": "我的脑内恋碍选项",
    "titleJP": "俺の脳内選択肢が、学園ラブコメを全力で邪魔している",
    "officalSite": "http://noucome.jp/",
    "weekDayJP": 4,
    "weekDayCN": 4,
    "timeJP": "0000",
    "timeCN": "0130",
    "onAirSite": [
      "http://comic.letv.com/zt/noucome/index.shtml",
      "http://www.bilibili.com/sp/我的脑内恋碍选项",
      "http://www.acfun.tv/a/aa96"
    ],
    "newBgm": true,
    "bgmId": 77570,
    "showDate": "2013-10-10"
  },
  "1310_21": {
    "titleCN": "没能做成勇者的我无可奈何的决定去工作",
    "titleJP": "勇者になれなかった俺はしぶしぶ就職を決意しました。",
    "officalSite": "http://yu-sibu.com/",
    "weekDayJP": 6,
    "weekDayCN": 6,
    "timeJP": "0030",
    "timeCN": "0200",
    "onAirSite": [
      "http://comic.letv.com/zt/dbcyzdw/index.shtml",
      "http://www.bilibili.com/sp/当不成勇者的我，只好认真找工作了。",
      "http://www.acfun.tv/a/aa102"
    ],
    "newBgm": true,
    "bgmId": 73440,
    "showDate": "2013-10-05"
  },
  "1310_22": {
    "titleCN": "东京暗鸦",
    "titleJP": "東京レイヴンズ",
    "officalSite": "http://www.tokyo-ravens.com/",
    "weekDayJP": 2,
    "weekDayCN": 2,
    "timeJP": "2330",
    "timeCN": "2330",
    "onAirSite": [
      "http://www.iqiyi.com/a_19rrgjanxt.html",
      "http://www.bilibili.com/sp/东京暗鸦",
      "http://www.acfun.tv/a/aa92"
    ],
    "newBgm": true,
    "bgmId": 78542,
    "showDate": "2013-10-08"
  },
  "1310_23": {
    "titleCN": "噬血狂袭",
    "titleJP": "ストライク・ザ・ブラッド",
    "officalSite": "http://www.strike-the-blood.com/",
    "weekDayJP": 5,
    "weekDayCN": 6,
    "timeJP": "2330",
    "timeCN": "",
    "onAirSite": [
      "http://www.bilibili.com/sp/STRIKE%20THE%20BLOOD",
      "http://www.acfun.tv/a/aa60"
    ],
    "newBgm": true,
    "bgmId": 67826,
    "showDate": "2013-10-04"
  },
  "1310_24": {
    "titleCN": "WHITE ALBUM2",
    "titleJP": "WHITE ALBUM2",
    "officalSite": "http://whitealbum2.jp/",
    "weekDayJP": 0,
    "weekDayCN": 0,
    "timeJP": "0030",
    "timeCN": "0030",
    "onAirSite": [
      "http://www.iqiyi.com/a_19rrgjanw9.html",
      "http://www.bilibili.com/sp/白色相簿2",
      "http://www.acfun.tv/a/aa104"
    ],
    "newBgm": true,
    "bgmId": 69496,
    "showDate": "2013-10-06"
  },
  "1310_25": {
    "titleCN": "零度战姬Vibration",
    "titleJP": "フリージング ヴァイブレーション",
    "officalSite": "http://freezing.tv/",
    "weekDayJP": 6,
    "weekDayCN": 0,
    "timeJP": "0000",
    "timeCN": "",
    "onAirSite": [
      "http://www.bilibili.com/sp/零度战姬",
      "http://www.acfun.tv/a/aa71"
    ],
    "newBgm": true,
    "bgmId": 78404,
    "showDate": "2013-10-05"
  },
  "1310_26": {
    "titleCN": "Little Busters! ～Refrain～",
    "titleJP": "リトルバスターズ！ ～Refrain～",
    "officalSite": "http://litbus-anime.com/refrain/",
    "weekDayJP": 6,
    "weekDayCN": 0,
    "timeJP": "2130",
    "timeCN": "0100",
    "onAirSite": [
      "http://tv.sohu.com/s2013/littlebusters2/",
      "http://www.bilibili.com/sp/LITTLE%20BUSTERS！",
      "http://www.acfun.tv/a/aa69"
    ],
    "newBgm": true,
    "bgmId": 69484,
    "showDate": "2013-10-05"
  },
  "1310_27": {
    "titleCN": "机巧少女不会受伤",
    "titleJP": "機巧少女は傷つかない",
    "officalSite": "http://www.machine-doll.com/",
    "weekDayJP": 1,
    "weekDayCN": 1,
    "timeJP": "2330",
    "timeCN": "2330",
    "onAirSite": [
      "http://www.iqiyi.com/a_19rrgjanhh.html",
      "http://www.bilibili.com/sp/机巧少女不会受伤",
      "http://www.acfun.tv/a/aa89"
    ],
    "newBgm": true,
    "bgmId": 61962,
    "showDate": "2013-10-07"
  },
  "1310_28": {
    "titleCN": "境界的彼方",
    "titleJP": "境界の彼方",
    "officalSite": "http://anime-kyokai.com/",
    "weekDayJP": 3,
    "weekDayCN": 4,
    "timeJP": "2330",
    "timeCN": "0300",
    "onAirSite": [
      "http://tv.sohu.com/s2013/jjdbf/",
      "http://www.bilibili.com/sp/境界的彼方",
      "http://www.acfun.tv/a/aa78"
    ],
    "newBgm": true,
    "bgmId": 49278,
    "showDate": "2013-10-02"
  },
  "1310_29": {
    "titleCN": "夜樱四重奏 ～花之歌～",
    "titleJP": "夜桜四重奏～ハナノウタ～",
    "officalSite": "http://yozakura-anime.jp/",
    "weekDayJP": 0,
    "weekDayCN": 1,
    "timeJP": "2230",
    "timeCN": "",
    "onAirSite": [
      "http://www.bilibili.com/sp/夜樱四重奏",
      "http://www.acfun.tv/a/aa72"
    ],
    "newBgm": true,
    "bgmId": 71955,
    "showDate": "2013-10-06"
  },
  "1310_30": {
    "titleCN": "黑子的篮球 2期",
    "titleJP": "黒子のバスケ 第2期",
    "officalSite": "http://www.kurobas.com/",
    "weekDayJP": 0,
    "weekDayCN": 1,
    "timeJP": "0058",
    "timeCN": "",
    "onAirSite": [
      "http://www.bilibili.com/sp/黑子的篮球",
      "http://www.acfun.tv/a/aa105"
    ],
    "newBgm": true,
    "bgmId": 77706,
    "showDate": "2013-10-06"
  },
  "1310_31": {
    "titleCN": "眼镜部",
    "titleJP": "メガネブ！",
    "officalSite": "http://mgnb.tv/",
    "weekDayJP": 0,
    "weekDayCN": 1,
    "timeJP": "2300",
    "timeCN": "0000",
    "onAirSite": [
      "http://www.iqiyi.com/a_19rrgjanth.html",
      "http://www.bilibili.com/sp/眼镜部！",
      "http://www.acfun.tv/a/aa91"
    ],
    "newBgm": true,
    "bgmId": 77479,
    "showDate": "2013-10-06"
  },
  "1310_32": {
    "titleCN": "魔笛MAGI 2期",
    "titleJP": "マギ 第2期",
    "officalSite": "http://www.project-magi.com/",
    "weekDayJP": 0,
    "weekDayCN": 0,
    "timeJP": "1600",
    "timeCN": "1605",
    "onAirSite": [
      "http://comic.letv.com/zt/magi2/index.shtml",
      "http://www.bilibili.com/sp/魔笛MAGI",
      "http://www.acfun.tv/a/aa107"
    ],
    "newBgm": true,
    "bgmId": 77646,
    "showDate": "2013-10-06"
  },
  "1310_33": {
    "titleCN": "宇宙兄弟",
    "titleJP": "宇宙兄弟",
    "officalSite": "http://www.ytv.co.jp/uchukyodai/",
    "weekDayJP": 6,
    "weekDayCN": 0,
    "timeJP": "1630",
    "timeCN": "",
    "onAirSite": [
      "http://www.bilibili.com/sp/宇宙兄弟",
      "http://www.acfun.tv/a/aa130"
    ],
    "newBgm": false,
    "bgmId": 28533,
    "showDate": "2012-04-01"
  },
  "1310_34": {
    "titleCN": "HUNTER×HUNTER",
    "titleJP": "HUNTER×HUNTER",
    "officalSite": "http://www.ntv.co.jp/hunterhunter/",
    "weekDayJP": 3,
    "weekDayCN": 4,
    "timeJP": "0029",
    "timeCN": "",
    "onAirSite": [
      "http://www.bilibili.com/sp/全职猎人",
      "http://www.acfun.tv/a/aa129"
    ],
    "newBgm": false,
    "bgmId": 10356,
    "showDate": "2011-10-03"
  },
  "1310_35": {
    "titleCN": "圣斗士星矢Ω",
    "titleJP": "聖闘士星矢Ω",
    "officalSite": "http://www.toei-anim.co.jp/tv/seiya/",
    "weekDayJP": 0,
    "weekDayCN": 1,
    "timeJP": "0530",
    "timeCN": "",
    "onAirSite": [
      "http://www.bilibili.com/sp/圣斗士星矢#S-226",
      "http://www.acfun.tv/a/aa134"
    ],
    "newBgm": false,
    "bgmId": 33446,
    "showDate": "2012-04-01"
  },
  "1310_36": {
    "titleCN": "口袋妖怪 XY",
    "titleJP": "ポケットモンスター XY",
    "officalSite": "http://www.tv-tokyo.co.jp/anime/pokemon_xy/",
    "weekDayJP": 4,
    "weekDayCN": 5,
    "timeJP": "1800",
    "timeCN": "",
    "onAirSite": [
      "http://www.bilibili.com/sp/宠物小精灵",
      "http://www.acfun.tv/a/aa109"
    ],
    "newBgm": true,
    "bgmId": 78799,
    "showDate": "2013-10-17"
  },
  "1310_37": {
    "titleCN": "飚速宅男",
    "titleJP": "弱虫ペダル",
    "officalSite": "http://yowapeda.com/",
    "weekDayJP": 2,
    "weekDayCN": 2,
    "timeJP": "0035",
    "timeCN": "0105",
    "onAirSite": [
      "http://www.youku.com/show_page/id_z88da380a055711e3b8b7.html",
      "http://www.bilibili.com/sp/飙速宅男"
    ],
    "newBgm": true,
    "bgmId": 59583,
    "showDate": "2013-10-08"
  },
  "1310_38": {
    "titleCN": "钻石王牌",
    "titleJP": "ダイヤのA",
    "officalSite": "http://diaace.com/",
    "weekDayJP": 0,
    "weekDayCN": 0,
    "timeJP": "0730",
    "timeCN": "1030",
    "onAirSite": [
      "http://www.iqiyi.com/a_19rrgjao65.html",
      "http://www.bilibili.com/sp/钻石王牌",
      "http://www.acfun.tv/sp/diamondace/"
    ],
    "newBgm": true,
    "bgmId": 73083,
    "showDate": "2013-10-06"
  },
  "1310_39": {
    "titleCN": "武士弗拉明戈",
    "titleJP": "サムライフラメンコ",
    "officalSite": "http://www.samumenco.com/",
    "weekDayJP": 5,
    "weekDayCN": 4,
    "timeJP": "0020",
    "timeCN": "0025",
    "onAirSite": [
      "http://comic.letv.com/zt/wsflmg/index.shtml",
      "http://www.bilibili.com/sp/武士弗拉明戈",
      "http://www.acfun.tv/a/aa100"
    ],
    "newBgm": true,
    "bgmId": 77473,
    "showDate": "2013-10-11"
  },
  "1310_40": {
    "titleCN": "伽利略少女",
    "titleJP": "ガリレイドンナ",
    "officalSite": "http://www.galileidonna.tv/",
    "weekDayJP": 4,
    "weekDayCN": 5,
    "timeJP": "2350",
    "timeCN": "0050",
    "onAirSite": [
      "http://comic.letv.com/zt/jllsn/index.shtml",
      "http://www.bilibili.com/sp/伽利略少女",
      "http://www.acfun.tv/a/aa99"
    ],
    "newBgm": true,
    "bgmId": 77471,
    "showDate": "2013-10-10"
  },
  "1310_41": {
    "titleCN": "Phi·Brain 神之谜题第三季",
    "titleJP": "ファイ・ブレイン３ 神のパズル",
    "officalSite": "http://www9.nhk.or.jp/anime/phibrain/index.html",
    "weekDayJP": 0,
    "weekDayCN": 1,
    "timeJP": "1630",
    "timeCN": "",
    "onAirSite": [
      "http://www.bilibili.com/sp/PHI·BRAIN%20神之谜题",
      "http://www.acfun.tv/a/aa74"
    ],
    "newBgm": true,
    "bgmId": 49693,
    "showDate": "2013-10-06"
  },
  "1310_42": {
    "titleCN": "记录的地平线",
    "titleJP": "ログ・ホライズン",
    "officalSite": "http://www9.nhk.or.jp/anime/loghorizon/",
    "weekDayJP": 6,
    "weekDayCN": 0,
    "timeJP": "1630",
    "timeCN": "",
    "onAirSite": [
      "http://www.bilibili.com/sp/记录的地平线",
      "http://www.acfun.tv/a/aa70"
    ],
    "newBgm": true,
    "bgmId": 64140,
    "showDate": "2013-10-05"
  },
  "1310_43": {
    "titleCN": "声优战队 Voice Storm 7",
    "titleJP": "声優戦隊ボイストーム７",
    "officalSite": "http://www.ntv.co.jp/voicetorm7/",
    "weekDayJP": 0,
    "weekDayCN": 1,
    "timeJP": "0105",
    "timeCN": "",
    "onAirSite": [
      "http://www.bilibili.com/sp/声优战队VOICESTORM7",
      "http://www.acfun.tv/a/aa61"
    ],
    "newBgm": true,
    "bgmId": 79467,
    "showDate": "2013-10-06"
  },
  "1310_44": {
    "titleCN": "第一神拳 Rising",
    "titleJP": "はじめの一歩 Rising",
    "officalSite": "http://www.ntv.co.jp/ippo/",
    "weekDayJP": 0,
    "weekDayCN": 1,
    "timeJP": "0035",
    "timeCN": "",
    "onAirSite": [
      "http://www.bilibili.com/sp/第一神拳",
      "http://www.acfun.tv/a/aa68"
    ],
    "newBgm": true,
    "bgmId": 78798,
    "showDate": "2013-10-06"
  },
  "1310_45": {
    "titleCN": "摸索吧！部活剧",
    "titleJP": "てさぐれ！部活もの",
    "officalSite": "http://www.ntv.co.jp/tesabu/",
    "weekDayJP": 0,
    "weekDayCN": 1,
    "timeJP": "2330",
    "timeCN": "",
    "onAirSite": [
      "http://www.bilibili.com/sp/摸索吧！部活剧",
      "http://www.acfun.tv/a/aa63"
    ],
    "newBgm": true,
    "bgmId": 80442,
    "showDate": "2013-10-06"
  },
  "1310_46": {
    "titleCN": "单色小姐",
    "titleJP": "ミス・モノクローム -The Animation-",
    "officalSite": "http://www.starchild.co.jp/special/miss_monochrome_anime/",
    "weekDayJP": 3,
    "weekDayCN": 4,
    "timeJP": "0035",
    "timeCN": "",
    "onAirSite": [],
    "newBgm": true,
    "bgmId": 80778,
    "showDate": "2013-10-02"
  },
  "1310_47": {
    "titleCN": "噗哔啵～来自未来～",
    "titleJP": "プピポー!",
    "officalSite": "http://pupipo.tv/",
    "weekDayJP": 6,
    "weekDayCN": 0,
    "timeJP": "0053",
    "timeCN": "",
    "onAirSite": [
      "http://www.bilibili.com/sp/噗哔啵%20来自未来",
      "http://www.acfun.tv/a/aa167"
    ],
    "newBgm": true,
    "bgmId": 88441,
    "showDate": "2013-12-21"
  },
  "1310_48": {
    "titleCN": "超青春姐弟s",
    "titleJP": "Super Seisyun Brothers -超青春姉弟s-",
    "officalSite": "http://ssb-love.tv/",
    "weekDayJP": 6,
    "weekDayCN": 0,
    "timeJP": "0053",
    "timeCN": "",
    "onAirSite": [
      "http://www.bilibili.com/sp/超青春姐弟S",
      "http://www.acfun.tv/a/aa59"
    ],
    "newBgm": false,
    "bgmId": 79701,
    "showDate": "2013-09-14"
  },
  "1310_49": {
    "titleCN": "悠哉日常大王",
    "titleJP": "のんのんびより",
    "officalSite": "http://www.nonnontv.com/",
    "weekDayJP": 2,
    "weekDayCN": 2,
    "timeJP": "0105",
    "timeCN": "0135",
    "onAirSite": [
      "http://www.youku.com/show_page/id_z838fc1c8030211e3b8b7.html",
      "http://www.bilibili.com/sp/悠哉日常大王",
      "http://www.acfun.tv/a/aa137"
    ],
    "newBgm": true,
    "bgmId": 78405,
    "showDate": "2013-10-08"
  },
  "1310_50": {
    "titleCN": "银狐",
    "titleJP": "ぎんぎつね",
    "officalSite": "http://gingitsune.net/",
    "weekDayJP": 1,
    "weekDayCN": 1,
    "timeJP": "0005",
    "timeCN": "0035",
    "onAirSite": [
      "http://www.youku.com/show_page/id_z0d2fcdb00a1f11e3a705.html",
      "http://www.bilibili.com/sp/银狐"
    ],
    "newBgm": true,
    "bgmId": 70960,
    "showDate": "2013-10-07"
  },
  "1310_51": {
    "titleCN": "少女骑士物语",
    "titleJP": "ワルキューレ ロマンツェ",
    "officalSite": "http://walroma.com/",
    "weekDayJP": 0,
    "weekDayCN": 0,
    "timeJP": "2330",
    "timeCN": "2330",
    "onAirSite": [
      "http://comic.letv.com/zt/snqswy/index.shtml",
      "http://www.bilibili.com/sp/少女骑士物语",
      "http://www.acfun.tv/a/aa106"
    ],
    "newBgm": true,
    "bgmId": 76210,
    "showDate": "2013-10-06"
  },
  "1310_52": {
    "titleCN": "来自风平浪静的明天",
    "titleJP": "凪のあすから",
    "officalSite": "http://www.nagiasu.jp/",
    "weekDayJP": 4,
    "weekDayCN": 5,
    "timeJP": "2130",
    "timeCN": "0000",
    "onAirSite": [
      "http://www.iqiyi.com/a_19rrgjao0x.html",
      "http://www.bilibili.com/sp/来自风平浪静的明天",
      "http://www.acfun.tv/a/aa95"
    ],
    "newBgm": true,
    "bgmId": 47889,
    "showDate": "2013-10-03"
  },
  "1310_53": {
    "titleCN": "黏黏糊糊角质君",
    "titleJP": "にゅるにゅる！！KAKUSENくん",
    "officalSite": "http://kakusen-kun.com/",
    "weekDayJP": 2,
    "weekDayCN": 3,
    "timeJP": "0059",
    "timeCN": "",
    "onAirSite": [
      "http://www.bilibili.com/sp/黏黏糊糊！！角质君"
    ],
    "newBgm": false,
    "bgmId": 77551,
    "showDate": "2013-07-09"
  },
  "1310_54": {
    "titleCN": "我要成为世界最强偶像",
    "titleJP": "世界でいちばん強くなりたい！",
    "officalSite": "http://www.sekatsuyo.com/",
    "weekDayJP": 0,
    "weekDayCN": 0,
    "timeJP": "2100",
    "timeCN": "2200",
    "onAirSite": [
      "http://data.movie.kankan.com/movie/74027",
      "http://www.bilibili.com/sp/我要成为世界最强偶像",
      "http://www.acfun.tv/a/aa73"
    ],
    "newBgm": true,
    "bgmId": 78408,
    "showDate": "2013-10-06"
  },
  "1310_55": {
    "titleCN": "网球并不可笑嘛 3期",
    "titleJP": "てーきゅう 第3期",
    "officalSite": "http://te-kyu.com/",
    "weekDayJP": 0,
    "weekDayCN": 1,
    "timeJP": "2125",
    "timeCN": "",
    "onAirSite": [
      "http://www.bilibili.com/sp/网球并不可笑嘛",
      "http://www.acfun.tv/a/aa110"
    ],
    "newBgm": true,
    "bgmId": 82079,
    "showDate": "2013-10-06"
  },
  "1310_56": {
    "titleCN": "限制级杀手",
    "titleJP": "殺し屋さん",
    "officalSite": "http://www.5648.jp/",
    "weekDayJP": 5,
    "weekDayCN": 6,
    "timeJP": "0000",
    "timeCN": "",
    "onAirSite": [
      "http://www.bilibili.com/sp/限制级杀手",
      "http://www.acfun.tv/a/aa62"
    ],
    "newBgm": true,
    "bgmId": 78398,
    "showDate": "2013-10-11"
  },
  "1310_57": {
    "titleCN": "魔鬼恋人",
    "titleJP": "DIABOLIK LOVERS",
    "officalSite": "http://anime-dialover.com/",
    "weekDayJP": 0,
    "weekDayCN": 1,
    "timeJP": "0030",
    "timeCN": "2330",
    "onAirSite": [
      "http://v.qq.com/cover/p/p5yfnziow4uwunf.html",
      "http://www.bilibili.com/sp/DIABOLIK%20LOVERS",
      "http://www.acfun.tv/a/aa93"
    ],
    "newBgm": false,
    "bgmId": 64993,
    "showDate": "2013-09-22"
  }
}